tonnelmp/__init__.py
tonnelmp/marketapi.py
tonnelmp/wtf.py
tonnelmp-1.2.dist-info/licenses/LICENSE
tonnelmp-1.2.dist-info/METADATA
tonnelmp-1.2.dist-info/WHEEL
tonnelmp-1.2.dist-info/top_level.txt
tonnelmp-1.2.dist-info/RECORD
