Metadata-Version: 2.4
Name: tonnelmp
Version: 1.2
Summary: A Python Module for interacting with Tonnel Marketplace API
Home-page: https://github.com/bleach-hub/tonnelmp
Author: bleach
Author-email: year0001@internet.ru
Classifier: Programming Language :: Python :: 3
Classifier: License :: OSI Approved :: MIT License
Requires-Python: >=3.8
License-File: LICENSE
Requires-Dist: curl_cffi>=0.5.7
Requires-Dist: pycryptodome>=3.19.1
Requires-Dist: fake_useragent>=2.2.0
Dynamic: author
Dynamic: author-email
Dynamic: classifier
Dynamic: description
Dynamic: description-content-type
Dynamic: home-page
Dynamic: license-file
Dynamic: requires-dist
Dynamic: requires-python
Dynamic: summary
